impax/__init__.py
impax/cli.py
impax/estimate.py
impax/impax.py
impax/mins.py
impax-0.1.2.dist-info/DESCRIPTION.rst
impax-0.1.2.dist-info/METADATA
impax-0.1.2.dist-info/RECORD
impax-0.1.2.dist-info/WHEEL
impax-0.1.2.dist-info/entry_points.txt
impax-0.1.2.dist-info/metadata.json
impax-0.1.2.dist-info/top_level.txt
