Metadata-Version: 2.0
Name: impax
Version: 0.1.2
Summary: Impact Forecasting for the Climate Impact Lab
Home-page: https://github.com/ClimateImpactLab/impax
Author: Justin Simcock
Author-email: jsimcock@rhg.com
License: MIT license
Keywords: impax
Platform: UNKNOWN
Classifier: Development Status :: 2 - Pre-Alpha
Classifier: Intended Audience :: Developers
Classifier: License :: OSI Approved :: MIT License
Classifier: Natural Language :: English
Classifier: Programming Language :: Python :: 2
Classifier: Programming Language :: Python :: 2.7
Classifier: Programming Language :: Python :: 3
Classifier: Programming Language :: Python :: 3.3
Classifier: Programming Language :: Python :: 3.4
Classifier: Programming Language :: Python :: 3.5
Requires-Dist: Click (>=6.0)
